biblehub/__init__.py
biblehub/scrape_passages.py
biblehub/scrape_search.py
biblehub/scrape_utils.py
biblehub/scrape_verses.py
biblehub/styling.py
biblehub-2.0.1.data/scripts/biblehub
biblehub-2.0.1.dist-info/LICENSE
biblehub-2.0.1.dist-info/METADATA
biblehub-2.0.1.dist-info/WHEEL
biblehub-2.0.1.dist-info/top_level.txt
biblehub-2.0.1.dist-info/RECORD
